LICENSE
MANIFEST.in
README
setup.py
data_packager/__init__.py
data_packager.egg-info/PKG-INFO
data_packager.egg-info/SOURCES.txt
data_packager.egg-info/dependency_links.txt
data_packager.egg-info/top_level.txt
data_packager/test/__init__.py
data_packager/test/asset_manager_test.py
data_packager/test/builder_test.py
data_packager/test/packager_test.py
data_packager/test/test-fixture-package/alt_resources/asset_a.txt
data_packager/test/test-fixture-package/alt_resources/asset_b.txt
data_packager/test/test-fixture-package/alt_resources/directory_asset
data_packager/test/test-fixture-package/tfp/assets/asset_a.txt
data_packager/test/test-fixture-package/tfp/assets/asset_b.txt
data_packager/test/test-fixture-package/tfp/assets/package_asset