Metadata-Version: 1.0
Name: data-packager
Version: 0.0.1
Summary: Provides dirt-simple tool for releasing datasets as packages
Home-page: https://github.com/ethanrowe/python-data-packager
Author: Ethan Rowe
Author-email: ethan@the-rowes.com
License: MIT
Platform: UNKNOWN
Classifier: Development Status :: 3 - Alpha
Classifier: Intended Audience :: Developers
Classifier: License :: OSI Approved :: MIT License
Classifier: Operating System :: OS Independent
Classifier: Programming Language :: Python :: 2.6
Classifier: Programming Language :: Python :: 2.7
Classifier: Topic :: Utilities
